snakist
