Metadata-Version: 2.1
Name: snakist
Version: 0.0.3
Summary: I hate camel
Home-page: https://github.com/caffeinism/snakist
Author: Kim Minjong
Author-email: make.dirty.code@gmail.com
License: MIT
Keywords: snake
Platform: UNKNOWN
